{
  "main": {
    "id": "7b54233430d82e5f",
    "type": "split",
    "children": [
      {
        "id": "c1e8ad6d2bd15a2d",
        "type": "tabs",
        "children": [
          {
            "id": "c8706d1c76d118fc",
            "type": "leaf",
            "state": {
              "type": "markdown",
              "state": {
                "file": "Worter/A/abschalten.md",
                "mode": "source",
                "source": false
              },
              "icon": "lucide-file",
              "title": "abschalten"
            }
          },
          {
            "id": "0f080a43b89ad45f",
            "type": "leaf",
            "state": {
              "type": "markdown",
              "state": {
                "file": "Worter/L/langfristig.md",
                "mode": "source",
                "source": false
              },
              "icon": "lucide-file",
              "title": "langfristig"
            }
          },
          {
            "id": "8b8b5ffc18fa689c",
            "type": "leaf",
            "state": {
              "type": "markdown",
              "state": {
                "file": "Wortlisten/0 Phrasen.md",
                "mode": "source",
                "source": false
              },
              "icon": "lucide-file",
              "title": "0 Phrasen"
            }
          },
          {
            "id": "350480742ec9264f",
            "type": "leaf",
            "state": {
              "type": "markdown",
              "state": {
                "file": "Lektionen/1-1/done/schriben/5 Krank.md",
                "mode": "source",
                "source": false
              },
              "icon": "lucide-file",
              "title": "5 Krank"
            }
          },
          {
            "id": "a56f0b4a474f4783",
            "type": "leaf",
            "state": {
              "type": "markdown",
              "state": {
                "file": "Worter/U/ununterbrochenen.md",
                "mode": "source",
                "source": false
              },
              "icon": "lucide-file",
              "title": "ununterbrochenen"
            }
          },
          {
            "id": "4ba8971615213af2",
            "type": "leaf",
            "state": {
              "type": "markdown",
              "state": {
                "file": "Worter/U/ununterbrochen.md",
                "mode": "source",
                "source": false
              },
              "icon": "lucide-file",
              "title": "ununterbrochen"
            }
          },
          {
            "id": "dd01f0cc44bebbb3",
            "type": "leaf",
            "state": {
              "type": "markdown",
              "state": {
                "file": "Worter/Waldabschnitt.md",
                "mode": "source",
                "source": false
              },
              "icon": "lucide-file",
              "title": "Waldabschnitt"
            }
          },
          {
            "id": "904e182b18006984",
            "type": "leaf",
            "state": {
              "type": "markdown",
              "state": {
                "file": "Worter/K/Küste.md",
                "mode": "source",
                "source": false
              },
              "icon": "lucide-file",
              "title": "Küste"
            }
          },
          {
            "id": "2875c4f6c065219a",
            "type": "leaf",
            "state": {
              "type": "markdown",
              "state": {
                "file": "Worter/U/unverzichtbar.md",
                "mode": "source",
                "source": false
              },
              "icon": "lucide-file",
              "title": "unverzichtbar"
            }
          }
        ],
        "currentTab": 3
      }
    ],
    "direction": "vertical"
  },
  "left": {
    "id": "1cd8d8654e644fb3",
    "type": "split",
    "children": [
      {
        "id": "5324c7a728bb0b3e",
        "type": "tabs",
        "children": [
          {
            "id": "e313be86e2286860",
            "type": "leaf",
            "state": {
              "type": "file-explorer",
              "state": {
                "sortOrder": "alphabetical",
                "autoReveal": false
              },
              "icon": "lucide-folder-closed",
              "title": "Files"
            }
          },
          {
            "id": "75a792a5ed66f125",
            "type": "leaf",
            "state": {
              "type": "search",
              "state": {
                "query": "",
                "matchingCase": false,
                "explainSearch": false,
                "collapseAll": false,
                "extraContext": false,
                "sortOrder": "alphabetical"
              },
              "icon": "lucide-search",
              "title": "Search"
            }
          },
          {
            "id": "621d716b36bf9bfd",
            "type": "leaf",
            "state": {
              "type": "bookmarks",
              "state": {},
              "icon": "lucide-bookmark",
              "title": "Bookmarks"
            }
          }
        ]
      }
    ],
    "direction": "horizontal",
    "width": 253.50271224975586
  },
  "right": {
    "id": "0ab1e072fc4dd144",
    "type": "split",
    "children": [
      {
        "id": "9ab2bdef50439334",
        "type": "tabs",
        "children": [
          {
            "id": "05f9db21a0491969",
            "type": "leaf",
            "state": {
              "type": "backlink",
              "state": {
                "file": "Worter/asdf.md",
                "collapseAll": false,
                "extraContext": false,
                "sortOrder": "alphabetical",
                "showSearch": false,
                "searchQuery": "",
                "backlinkCollapsed": false,
                "unlinkedCollapsed": true
              },
              "icon": "links-coming-in",
              "title": "Backlinks for asdf"
            }
          },
          {
            "id": "39bc8165d6b03546",
            "type": "leaf",
            "state": {
              "type": "outgoing-link",
              "state": {
                "linksCollapsed": false,
                "unlinkedCollapsed": true
              },
              "icon": "links-going-out",
              "title": "Outgoing links"
            }
          },
          {
            "id": "aa2e7e72196c6ab6",
            "type": "leaf",
            "state": {
              "type": "tag",
              "state": {
                "sortOrder": "frequency",
                "useHierarchy": true,
                "showSearch": false,
                "searchQuery": ""
              },
              "icon": "lucide-tags",
              "title": "Tags"
            }
          },
          {
            "id": "d61fe203211a722e",
            "type": "leaf",
            "state": {
              "type": "outline",
              "state": {
                "file": "Worter/H/hinzufügen.md",
                "followCursor": false,
                "showSearch": false,
                "searchQuery": ""
              },
              "icon": "lucide-list",
              "title": "Outline of hinzufügen"
            }
          }
        ]
      }
    ],
    "direction": "horizontal",
    "width": 300,
    "collapsed": true
  },
  "left-ribbon": {
    "hiddenItems": {
      "switcher:Open quick switcher": false,
      "graph:Open graph view": false,
      "canvas:Create new canvas": false,
      "daily-notes:Open today's daily note": false,
      "templates:Insert template": false,
      "command-palette:Open command palette": false,
      "audio-recorder:Start/stop recording": false,
      "obsidian-kanban:Create new board": false
    }
  },
  "active": "350480742ec9264f",
  "lastOpenFiles": [
    "Lektionen/1-1/done/schriben/4 Autofrei.md",
    "Lektionen/1-1/done/schriben/3 Soll man Geld spenden?.md",
    "Lektionen/1-1/done/schriben/1 Wer bin ich und was mache ich hier?.md",
    "Lektionen/C1/Schriben.md",
    "Texte/c1/schriben/Themen.md",
    "Texte/c1/schriben/Arbeiten im Homeoffice.md",
    "Texte/c1/schriben/Themen/Technologie und Digitalisierung.md",
    "Lektionen/C1/wip/Untitled.md",
    "Lektionen/C1/Sprechen.md",
    "Lektionen/C1/Prompt.md",
    "Wortlisten/Negationspartikel.md",
    "Wortlisten/Partikel.md",
    "Texte/c1/Umwelt/2 Bäumepflanzen für das Klima.md",
    "Worter/K/komplex.md",
    "Worter/Saatgutsammler.md",
    "Texte/c1/Umwelt/1,5 Grad-Ziel Wie sich das Klima jetzt noch retten lässt.md",
    "Texte/c1/shorts/1. 606 Euro mehr Diät für Abgeordnete? 😱.md",
    "Worter/Nehbensatz.md",
    "Worter/E/Entscheidungen.md",
    "Worter/E/Entscheidung.md",
    "Worter/Klimaabkommen.md",
    "Texte/c1/shorts/3. Schuldenpaket. Vergeigen es die Grünen?.md",
    "Texte/c1/shorts/2. Warum Amthor & die CDU gefährlich werden....md",
    "Texte/c1/jul/0.md",
    "Lektionen/1-1/done/lesen/3  Ein Selbstversuch als Hobbybäuerin.md",
    "Lektionen/1-1/done/lesen/2 Unter Druck nach oben.md",
    "Texte/c1/Wissenschaft",
    "Texte/c1/Umwelt",
    "Texte/c1/MOdel",
    "Worter/4",
    "Lektionen/1-1/done/schriben/Untitled",
    "Lektionen/C1/wip",
    "Lektionen/C1",
    "Lektionen/1-1/done/mick",
    "Lektionen/1-1/done/schriben",
    "Lektionen/1-1/done/lesen",
    "Anhänge/Pasted image 20250224055949.png",
    "Anhänge/Pasted image 20250224055705.png",
    "Anhänge/Pasted image 20250224055357.png",
    "Anhänge/Pasted image 20250222100655.png",
    "Anhänge/pronomen.png",
    "Anhänge/Pasted image 20250203051744.png",
    "Anhänge/Pasted image 20250127154728.png",
    "Anhänge/Pasted image 20250203084709.png",
    "Anhänge/Pasted image 20250203051808.png",
    "Anhänge/Pasted image 20250125084340.png"
  ]
}