{
  "main": {
    "id": "221ea04d7b896dfd",
    "type": "split",
    "children": [
      {
        "id": "64829a584100b245",
        "type": "tabs",
        "children": [
          {
            "id": "bb0c7bacc1179ec5",
            "type": "leaf",
            "state": {
              "type": "markdown",
              "state": {
                "file": "Wortlisten/100 verbs.md",
                "mode": "source",
                "source": false
              }
            }
          },
          {
            "id": "364d740ec6a7c366",
            "type": "leaf",
            "state": {
              "type": "markdown",
              "state": {
                "file": "Texte/Welt/Delivery.md",
                "mode": "source",
                "source": false
              }
            }
          },
          {
            "id": "a0fbdcce3ff8c255",
            "type": "leaf",
            "state": {
              "type": "markdown",
              "state": {
                "file": "Wörter/voraussichtlich.md",
                "mode": "source",
                "source": false
              }
            }
          },
          {
            "id": "811bfcb6e437cd4b",
            "type": "leaf",
            "state": {
              "type": "markdown",
              "state": {
                "file": "Wörter/zugestellt.md",
                "mode": "source",
                "source": false
              }
            }
          },
          {
            "id": "9e47613819c1b3aa",
            "type": "leaf",
            "state": {
              "type": "markdown",
              "state": {
                "file": "Wörter/vorbereiten.md",
                "mode": "source",
                "source": false
              }
            }
          }
        ],
        "currentTab": 2
      }
    ],
    "direction": "vertical"
  },
  "left": {
    "id": "11b84d145109f361",
    "type": "split",
    "children": [
      {
        "id": "0372cc9342a26192",
        "type": "tabs",
        "children": [
          {
            "id": "d0dd1351b59a3225",
            "type": "leaf",
            "state": {
              "type": "file-explorer",
              "state": {
                "sortOrder": "alphabetical"
              }
            }
          },
          {
            "id": "2c572581800d3354",
            "type": "leaf",
            "state": {
              "type": "search",
              "state": {
                "query": "ziehen",
                "matchingCase": false,
                "explainSearch": false,
                "collapseAll": false,
                "extraContext": false,
                "sortOrder": "alphabetical"
              }
            }
          },
          {
            "id": "e6b68bd3d7724240",
            "type": "leaf",
            "state": {
              "type": "bookmarks",
              "state": {}
            }
          }
        ]
      }
    ],
    "direction": "horizontal",
    "width": 200
  },
  "right": {
    "id": "515e4d54eb84c724",
    "type": "split",
    "children": [
      {
        "id": "4531bcf68f6c5416",
        "type": "tabs",
        "children": [
          {
            "id": "c03c8f70a63e6155",
            "type": "leaf",
            "state": {
              "type": "backlink",
              "state": {
                "file": "Wörter/voraussichtlich.md",
                "collapseAll": false,
                "extraContext": false,
                "sortOrder": "alphabetical",
                "showSearch": false,
                "searchQuery": "",
                "backlinkCollapsed": false,
                "unlinkedCollapsed": true
              }
            }
          },
          {
            "id": "4d214b6f738eafb0",
            "type": "leaf",
            "state": {
              "type": "outgoing-link",
              "state": {
                "file": "Wörter/voraussichtlich.md",
                "linksCollapsed": false,
                "unlinkedCollapsed": true
              }
            }
          },
          {
            "id": "b0a68252545bb3a8",
            "type": "leaf",
            "state": {
              "type": "tag",
              "state": {
                "sortOrder": "frequency",
                "useHierarchy": true
              }
            }
          },
          {
            "id": "4673c4d4e694df2b",
            "type": "leaf",
            "state": {
              "type": "outline",
              "state": {
                "file": "Wörter/voraussichtlich.md"
              }
            }
          }
        ],
        "currentTab": 2
      }
    ],
    "direction": "horizontal",
    "width": 476.5,
    "collapsed": true
  },
  "left-ribbon": {
    "hiddenItems": {
      "audio-recorder:Start/stop recording": false,
      "switcher:Open quick switcher": false,
      "graph:Open graph view": false,
      "canvas:Create new canvas": false,
      "daily-notes:Open today's daily note": false,
      "templates:Insert template": false,
      "command-palette:Open command palette": false,
      "obsidian-excalidraw-plugin:Create new drawing": false,
      "templater-obsidian:Templater": false,
      "table-editor-obsidian:Advanced Tables Toolbar": false,
      "omnisearch:Omnisearch": false
    }
  },
  "active": "a0fbdcce3ff8c255",
  "lastOpenFiles": [
    "Wörter/zugestellt.md",
    "Wörter/voraussichtlich.md",
    "Wörter/zugestelltsten.md",
    "Wörter/zugestellter.md",
    "Texte/Welt/Delivery.md",
    "Wörter/sichtlich.md",
    "Wörter/sichtlichsten.md",
    "Wörter/sichtlicher.md",
    "Wörter/voraussichtlichsten.md",
    "Wörter/voraussichtlicher.md",
    "Wörter/vorbereiten.md",
    "Wörter/bereite vor.md",
    "Wörter/vorbereitet.md",
    "Wörter/bereitete vor.md",
    "Wörter/Hilfreiche.md",
    "Wörter/hilfreich.md",
    "Wörter/hilfreichsten.md",
    "Wörter/hilfreicher.md",
    "Wörter/Sendung.md",
    "Wörter/Sendungen.md",
    "Wortlisten/100 verbs.md",
    "Wörter/freigegeben.md",
    "Wörter/freigegebensten.md",
    "Wörter/freigegebener.md",
    "Wörter/Zustellung.md",
    "Wörter/Zustellungen.md",
    "Texte/Welt",
    "Anhänge/Pasted image 20240804150741.png",
    "Anhänge/Pasted image 20240729135443.png",
    "Anhänge/Pasted image 20240729135330.png",
    "Anhänge/Pasted image 20240729135226.png",
    "Anhänge/Pasted image 20240729135147.png",
    "Anhänge/Pasted image 20240729134938.png",
    "Anhänge/Pasted image 20240729134659.png",
    "Anhänge/Pasted image 20240729133936.png",
    "Anhänge/Pasted image 20240729133800.png",
    "Anhänge/Pasted image 20240729133715.png",
    "Wörter/Adverbien",
    "smart-chats",
    "Texte/Skripte/Muzzy",
    "Untitled 2.canvas",
    "Untitled.canvas",
    "Untitled 1.canvas",
    "Lektionen/Intensiv/A2.1 Kursbuch",
    "Lektionen/Intensiv/A2.1 Arbeitsbuch",
    "Lektionen/Intensiv",
    "Texte/Gedichte/Kinder",
    "Wortlisten/IMG_5118.MOV",
    "Texte/Skripte/extra",
    "Texte/Ditor/Positionen.canvas"
  ]
}